anasyspythontools/__init__.py
anasyspythontools/anasysdoc.py
anasyspythontools/anasysfile.py
anasyspythontools/anasysio.py
anasyspythontools/anasysnanoTA.py
anasyspythontools/export.py
anasyspythontools/heightmap.py
anasyspythontools/image.py
anasyspythontools/irspectra.py
anasyspythontools/plotting.py
anasyspythontools/repr_dict.py
anasyspythontools/repr_utils.py
anasyspythontools/xarray_utils.py
anasyspythontools-0.5.2.dist-info/METADATA
anasyspythontools-0.5.2.dist-info/WHEEL
anasyspythontools-0.5.2.dist-info/licenses/LICENSE.txt
anasyspythontools-0.5.2.dist-info/RECORD
