Metadata-Version: 2.3
Name: anasyspythontools
Version: 0.5.2
Summary: A suite of Python tools for use with Analysis Studio AFM-IR files.
Project-URL: Homepage, https://github.com/GeorgRamer/anasys-python-tools
Author-email: Georg Ramer <georg.ramer@tuwien.ac.at>, Wouter Duverger <wouter.duverger@kuleuven.be>, Cody Schindler <cschindler@anasysinstruments.com>
License: MIT
Keywords: .axd,.axz,AFM,AFM-IR,Anasys,Instruments,atomic,axd,axz,force,hyperspectral,infrared,microscope,microscopy,s-snom,spectra,spectroscopy,spectrum,ssnom
Classifier: Development Status :: 4 - Beta
Classifier: Intended Audience :: Science/Research
Classifier: License :: OSI Approved :: MIT License
Classifier: Programming Language :: Python :: 3.6
Classifier: Topic :: Scientific/Engineering :: Chemistry
Classifier: Topic :: Scientific/Engineering :: Information Analysis
Requires-Python: >=3.8
Requires-Dist: ipython>=7.0
Requires-Dist: matplotlib-scalebar>=0.8.1
Requires-Dist: matplotlib>=3.5.3
Requires-Dist: numpy>=1.22
Requires-Dist: scipy>=1.9.1
Requires-Dist: xarray>=2022.6.0
